hasanpy/__init__.py
hasanpy/__main__.py
hasanpy/compiler.py
hasanpy/vm.py
hasanpy-0.1.1.dist-info/entry_points.txt
hasanpy-0.1.1.dist-info/LICENSE
hasanpy-0.1.1.dist-info/WHEEL
hasanpy-0.1.1.dist-info/METADATA
hasanpy-0.1.1.dist-info/RECORD
